pythistic/Chart.py
pythistic/FrequencyTable.py
pythistic/Transform.py
pythistic/__init__.py
Pythistic-1.1.1.dist-info/LICENSE
Pythistic-1.1.1.dist-info/METADATA
Pythistic-1.1.1.dist-info/WHEEL
Pythistic-1.1.1.dist-info/top_level.txt
Pythistic-1.1.1.dist-info/RECORD
