Metadata-Version: 2.1
Name: Pythistic
Version: 1.1.1
Summary: A Python library for statistical data processing
Home-page: https://github.com/brotherzhafif/Pythistic
Author: BrotherZhafif
Author-email: bangz1504@gmail.com
License: MIT
Platform: UNKNOWN
Classifier: Programming Language :: Python :: 3
Classifier: License :: OSI Approved :: MIT License
Classifier: Operating System :: OS Independent
Requires-Python: >=3.6
Requires-Dist: matplotlib
Requires-Dist: matplotlib-venn
Requires-Dist: numpy
Requires-Dist: pandas
Requires-Dist: scipy
Requires-Dist: tabulate
